probabilistic_model/__init__.py
probabilistic_model/constants.py
probabilistic_model/error.py
probabilistic_model/monte_carlo_estimator.py
probabilistic_model/probabilistic_model.py
probabilistic_model/utils.py
probabilistic_model/bayesian_network/__init__.py
probabilistic_model/bayesian_network/bayesian_network.py
probabilistic_model/distributions/__init__.py
probabilistic_model/distributions/distributions.py
probabilistic_model/distributions/gaussian.py
probabilistic_model/distributions/helper.py
probabilistic_model/distributions/multinomial.py
probabilistic_model/distributions/uniform.py
probabilistic_model/interfaces/__init__.py
probabilistic_model/interfaces/mlflow_integration.py
probabilistic_model/interfaces/drawio/__init__.py
probabilistic_model/interfaces/drawio/drawio.py
probabilistic_model/interfaces/drawio/exporter.py
probabilistic_model/learning/__init__.py
probabilistic_model/learning/nyga_distribution.py
probabilistic_model/learning/jpt/__init__.py
probabilistic_model/learning/jpt/jpt.py
probabilistic_model/learning/jpt/variables.py
probabilistic_model/learning/region_graph/__init__.py
probabilistic_model/learning/region_graph/region_graph.py
probabilistic_model/probabilistic_circuit/__init__.py
probabilistic_model/probabilistic_circuit/jax/__init__.py
probabilistic_model/probabilistic_circuit/jax/coupling_circuit.py
probabilistic_model/probabilistic_circuit/jax/discrete_layer.py
probabilistic_model/probabilistic_circuit/jax/gaussian_layer.py
probabilistic_model/probabilistic_circuit/jax/inner_layer.py
probabilistic_model/probabilistic_circuit/jax/input_layer.py
probabilistic_model/probabilistic_circuit/jax/probabilistic_circuit.py
probabilistic_model/probabilistic_circuit/jax/uniform_layer.py
probabilistic_model/probabilistic_circuit/jax/utils.py
probabilistic_model/probabilistic_circuit/rx/__init__.py
probabilistic_model/probabilistic_circuit/rx/helper.py
probabilistic_model/probabilistic_circuit/rx/probabilistic_circuit.py
probabilistic_model-7.1.1.dist-info/METADATA
probabilistic_model-7.1.1.dist-info/WHEEL
probabilistic_model-7.1.1.dist-info/top_level.txt
probabilistic_model-7.1.1.dist-info/RECORD
