Metadata-Version: 2.4
Name: probabilistic_model
Version: 7.1.1
Summary: Models for probabilistic reasoning
Author-email: Tom Schierenbeck <tom_sch@uni-bremen.de>
Project-URL: Source, https://github.com/probabilistic_model/probabilistic_model
Project-URL: Bug Tracker, https://github.com/tomsch420/probabilistic_model/issues
Keywords: probabilistic models,probabilistic machine learning,probability theory,variables,reasoning under uncertainty
Classifier: Programming Language :: Python :: 3
Classifier: License :: OSI Approved :: MIT License
Classifier: Operating System :: OS Independent
Requires-Python: >=3.6
Requires-Dist: random-events>=4.1.2
Requires-Dist: networkx
Requires-Dist: plotly
Requires-Dist: scipy
Requires-Dist: typing_extensions
Requires-Dist: numpy
Requires-Dist: sortedcontainers
Requires-Dist: tqdm
Requires-Dist: tabulate
Requires-Dist: N2G
Requires-Dist: python-igraph
Requires-Dist: rustworkx>=0.16.0
